mara_client/__init__.py
mara_client/clients.py
mara_client/models.py
mara_client/utils.py
mara_client-0.20.3.dist-info/METADATA
mara_client-0.20.3.dist-info/WHEEL
mara_client-0.20.3.dist-info/top_level.txt
mara_client-0.20.3.dist-info/RECORD
