Metadata-Version: 2.4
Name: mara_client
Version: 0.20.3
Summary: A client for the MARA conversational agent for cheminformatics.
Home-page: https://nanome.ai/mara
Author: Sam Hessenauer, Alex McNerney, Mike Rosengrant
Author-email: sam@nanome.ai, alex@nanome.ai, mike.rosengrant@nanome.ai
Classifier: Programming Language :: Python :: 3
Classifier: Operating System :: OS Independent
Requires-Dist: requests>=2.31.0
Requires-Dist: pandas>=2.1.4
Requires-Dist: pydantic>=2.7.3
Dynamic: author
Dynamic: author-email
Dynamic: classifier
Dynamic: description
Dynamic: description-content-type
Dynamic: home-page
Dynamic: requires-dist
Dynamic: summary
